argsv/__init__.py
argsv/_meta.py
argsv/_pattern.py
argsv/_validators.py
argsv/errors.py
argsv/validation.py
argsv/validators.py
argsv-0.1.0.dist-info/LICENSE
argsv-0.1.0.dist-info/METADATA
argsv-0.1.0.dist-info/WHEEL
argsv-0.1.0.dist-info/top_level.txt
argsv-0.1.0.dist-info/RECORD
