Metadata-Version: 2.2
Name: argsv
Version: 0.1.0
Summary: argsv is a library for validating arguments passed to callables. With this library, you can validate arguments sent to callables in a simpler, more readable, and well-defined context.
Home-page: https://github.com/mimseyedi/argsv
Author: mimseyedi
Author-email: mim.seyedi@gmail.com
License: GNU General Public License v3 (GPLv3)
Keywords: argsv,argument_validation,Python,package,validatevalidation,validator,decorator
Classifier: License :: OSI Approved :: GNU General Public License v3 (GPLv3)
Classifier: Programming Language :: Python :: 3
Classifier: Programming Language :: Python :: 3.10
Classifier: Programming Language :: Python :: 3.11
Classifier: Programming Language :: Python :: 3.12
Requires-Python: >=3.10
License-File: LICENSE
Dynamic: author
Dynamic: author-email
Dynamic: classifier
Dynamic: description
Dynamic: description-content-type
Dynamic: home-page
Dynamic: keywords
Dynamic: license
Dynamic: requires-python
Dynamic: summary
